accelo_mlops/__init__.py
accelo_mlops/accelo_client.py
accelo_mlops/api/__init__.py
accelo_mlops/api/mlops_api.py
accelo_mlops/api/torch_api.py
accelo_mlops/entities/__init__.py
accelo_mlops/entities/actual.py
accelo_mlops/entities/assembly.py
accelo_mlops/entities/asset.py
accelo_mlops/entities/baseline.py
accelo_mlops/entities/data.py
accelo_mlops/entities/feature.py
accelo_mlops/entities/metadata.py
accelo_mlops/entities/model.py
accelo_mlops/entities/prediction.py
accelo_mlops/entities/snapshot.py
accelo_mlops/utils/UserResponsePrettify.py
accelo_mlops/utils/__init__.py
accelo_mlops/utils/api_utils.py
accelo_mlops/utils/constants.py
accelo_mlops/utils/errors.py
accelo_mlops/utils/file_format_utils.py
accelo_mlops/utils/time_utils.py
examples/__init__.py
examples/test.py
examples/deposit_prediction/__init__.py
examples/deposit_prediction/deposit_prediction.py
accelo-0.0.1.dist-info/LICENSE
accelo-0.0.1.dist-info/METADATA
accelo-0.0.1.dist-info/WHEEL
accelo-0.0.1.dist-info/top_level.txt
accelo-0.0.1.dist-info/RECORD
