Metadata-Version: 2.1
Name: accelo
Version: 0.0.1
Summary: UNKNOWN
Home-page: https://acceldata.io
Author: Acceldata
Author-email: support@acceldata.io
License: BSD
Keywords: accelo
Platform: UNKNOWN
Classifier: License :: OSI Approved :: BSD License
Classifier: Programming Language :: Python :: 3
Classifier: Programming Language :: Python :: 3.7
Requires-Dist: pandas
Requires-Dist: numpy
Requires-Dist: requests
Requires-Dist: dataclasses
Requires-Dist: sqlalchemy
Requires-Dist: joblib
Requires-Dist: psycopg2-binary
Requires-Dist: boto3 (>=1.17)
Requires-Dist: pyarrow (>=3.0.0)
Requires-Dist: fsspec (>=0.8.7)
